README.rst
setup.py
marian/__init__.py
marian/app.py
marian/fast_arrow_quiver.py
marian/version.py
marian.egg-info/PKG-INFO
marian.egg-info/SOURCES.txt
marian.egg-info/dependency_links.txt
marian.egg-info/top_level.txt