Metadata-Version: 2.1
Name: marian
Version: 0.0.16
Summary: a personal Robinhood API server built on Fast Arrow.
Home-page: https://github.com/nebulousdog/marian
Author: Tom Spalding
Author-email: tom@blackforestbotanics.com
License: MIT
Platform: UNKNOWN
Classifier: Framework :: Flask
Classifier: Programming Language :: Python :: 3
Classifier: License :: OSI Approved :: MIT License
